simple_orm/__init__.py
simple_orm/basic_orm.py
simple_orm_sqlite-0.0.3.dist-info/licenses/LICENSE
simple_orm_sqlite-0.0.3.dist-info/METADATA
simple_orm_sqlite-0.0.3.dist-info/WHEEL
simple_orm_sqlite-0.0.3.dist-info/top_level.txt
simple_orm_sqlite-0.0.3.dist-info/RECORD
