Metadata-Version: 2.4
Name: simple-orm-sqlite
Version: 0.0.3
Summary: Basic Orm for sqlite
Author: Danilo Souza
Author-email: danilocrautomacao@gmail.com
License: MIT License
Keywords: sqlite orm
License-File: LICENSE
Dynamic: author
Dynamic: author-email
Dynamic: description
Dynamic: description-content-type
Dynamic: keywords
Dynamic: license
Dynamic: license-file
Dynamic: summary
